writetight/__init__.py
writetight/main.py
writetight/nlp.py
writetight/pattern_questions.py
writetight/patterns.py
write_tight-0.4.3.dist-info/LICENSE
write_tight-0.4.3.dist-info/METADATA
write_tight-0.4.3.dist-info/WHEEL
write_tight-0.4.3.dist-info/entry_points.txt
write_tight-0.4.3.dist-info/top_level.txt
write_tight-0.4.3.dist-info/RECORD
