Metadata-Version: 2.1
Name: write-tight
Version: 0.4.3
Summary: Write tight helps you to say exactly what you want with precision and power.
Author-email: Ernst Bolle <ernst-bolle@bolle-data-consultancy.nl>
Project-URL: Homepage, https://github.com/EBolle/write-tight
Requires-Python: >=3.11
License-File: LICENSE
Requires-Dist: spacy ==3.7.2
